CA/Assinment3/majorityDesign.v
module majority(input a,input b,input c,output z);
	assign z=(a&b)|(b&c)|(c&a);
endmodule

CA/Assinment3/majorTest.v
module testbench();
	reg a,b,c;
	wire z;
	majority uut(.a(a),.b(b),.c(c),.z(z));
	initial begin
		$dumpfile("dump.vcd");
		$dumpvars(0,testbench);
		a=0;b=0;c=0;#10;
		a=0;b=0;c=1;#10;
		a=0;b=1;c=0;#10;
		a=0;b=1;c=1;#10;
		a=1;b=0;c=0;#10;
		a=1;b=0;c=1;#10;
		a=1;b=1;c=0;#10;
		a=1;b=1;c=1;#10; 
	end
endmodule

CA/Assinment3/dump.vcd
$date
	Wed May  6 14:53:54 2026
$end
$version
	Icarus Verilog
$end
$timescale
	1s
$end
$scope module testbench $end
$var wire 1 ! z $end
$var reg 1 " a $end
$var reg 1 # b $end
$var reg 1 $ c $end
$scope module uut $end
$var wire 1 " a $end
$var wire 1 # b $end
$var wire 1 $ c $end
$var wire 1 ! z $end
$upscope $end
$upscope $end
$enddefinitions $end
#0
$dumpvars
0$
0#
0"
0!
$end
#10
1$
#20
0$
1#
#30
1!
1$
#40
0!
0$
0#
1"
#50
1!
1$
#60
0$
1#
#70
1$
