CA/Assignment4/decoderThreeTEight.v
module decoder3to8 (input  [2:0] a,output [7:0] y);
    assign y = (a == 3'b000) ? 8'b00000001 :
               (a == 3'b001) ? 8'b00000010 :
               (a == 3'b010) ? 8'b00000100 :
               (a == 3'b011) ? 8'b00001000 :
               (a == 3'b100) ? 8'b00010000 :
               (a == 3'b101) ? 8'b00100000 :
               (a == 3'b110) ? 8'b01000000 :
                               8'b10000000;
endmodule

CA/Assignment4/testDecoderThreeToeight.v
module threeEtoEightDTest();
    reg  [2:0] a;
    wire [7:0] y;
    decoder3to8 uut (.a(a),.y(y));

    initial begin
        $dumpfile("dump.vcd");
        $dumpvars;

        a = 3'b000; #10;
        a = 3'b001; #10;
        a = 3'b010; #10;
        a = 3'b011; #10;
        a = 3'b100; #10;
        a = 3'b101; #10;
        a = 3'b110; #10;
        a = 3'b111; #10;
    end

endmodule

CA/Assignment4/dump.vcd
$date
	Wed May 20 15:33:28 2026
$end
$version
	Icarus Verilog
$end
$timescale
	1s
$end
$scope module threeEtoEightDTest $end
$var wire 8 ! y [7:0] $end
$var reg 3 " a [2:0] $end
$scope module uut $end
$var wire 3 # a [2:0] $end
$var wire 8 $ y [7:0] $end
$upscope $end
$upscope $end
$enddefinitions $end
#0
$dumpvars
b1 $
b0 #
b0 "
b1 !
$end
#10
b10 !
b10 $
b1 "
b1 #
#20
b100 !
b100 $
b10 "
b10 #
#30
b1000 !
b1000 $
b11 "
b11 #
#40
b10000 !
b10000 $
b100 "
b100 #
#50
b100000 !
b100000 $
b101 "
b101 #
#60
b1000000 !
b1000000 $
b110 "
b110 #
#70
b10000000 !
b10000000 $
b111 "
b111 #
